pycounts_mjhz/__init__.py
pycounts_mjhz/plotting.py
pycounts_mjhz/pycounts.py
pycounts_mjhz-0.1.1.dist-info/LICENSE
pycounts_mjhz-0.1.1.dist-info/METADATA
pycounts_mjhz-0.1.1.dist-info/WHEEL
pycounts_mjhz-0.1.1.dist-info/RECORD
