Metadata-Version: 2.1
Name: pycounts_mjhz
Version: 0.1.1
Summary: Calculate word counts in a text file! A toy python package made for DSCI 524
License: MIT
Author: Mona Zhu
Requires-Python: >=3.9,<4.0
Classifier: License :: OSI Approved :: MIT License
Classifier: Programming Language :: Python :: 3
Classifier: Programming Language :: Python :: 3.9
Classifier: Programming Language :: Python :: 3.10
Classifier: Programming Language :: Python :: 3.11
Classifier: Programming Language :: Python :: 3.12
Requires-Dist: matplotlib (>=3.8.2,<4.0.0)
